iro/console.py
iro/main.cpp
iro/main.py
toori_server-1.1.10.data/data/iro/main.cpp
toori_server-1.1.10.dist-info/METADATA
toori_server-1.1.10.dist-info/WHEEL
toori_server-1.1.10.dist-info/entry_points.txt
toori_server-1.1.10.dist-info/top_level.txt
toori_server-1.1.10.dist-info/RECORD
