Metadata-Version: 2.1
Name: toori-server
Version: 1.1.10
Summary: Server for a minimal layer 3 tunnel over http(s).
Home-page: https://github.com/kokseen1/Iro
License: UNKNOWN
Platform: UNKNOWN
Requires-Python: >=3.7
Requires-Dist: python-socketio
Requires-Dist: scapy
Requires-Dist: sanic
